kontakt/__init__.py
kontakt/config_options.py
kontakt/examples/__init__.py
kontakt/examples/configurable_extension.py
kontakt/examples/extension.py
kontakt-5.0.0.dist-info/licenses/LICENSE
kontakt-5.0.0.dist-info/METADATA
kontakt-5.0.0.dist-info/WHEEL
kontakt-5.0.0.dist-info/entry_points.txt
kontakt-5.0.0.dist-info/top_level.txt
kontakt-5.0.0.dist-info/zip-safe
kontakt-5.0.0.dist-info/RECORD
