Metadata-Version: 2.4
Name: kontakt
Version: 5.0.0
Summary: Foundation for adding extensibility to Python packages.
Author-email: Sixty North AS <systems+kontakt@sixty-north.com>
Project-URL: repository, https://bitbucket.org/sixty-north/kontakt
Classifier: Development Status :: 5 - Production/Stable
Classifier: Environment :: Console
Classifier: Intended Audience :: Information Technology
Classifier: License :: Other/Proprietary License
Classifier: Programming Language :: Python :: 3
Requires-Python: >=3.11
License-File: LICENSE
Requires-Dist: asq>=1.3
Requires-Dist: dendrodict>=1.0.4
Requires-Dist: stevedore>=5.1.0
Dynamic: license-file
